bencode_c/__init__.py
bencode_c/__init__.pyi
bencode_c/_bencode.pyd
bencode_c/bencode.c
bencode_c/common.h
bencode_c/ctx.h
bencode_c/decode.c
bencode_c/encode.c
bencode_c/overflow.h
bencode_c/py.typed
bencode_c/str.h
bencode_c-0.0.14.dist-info/METADATA
bencode_c-0.0.14.dist-info/WHEEL
bencode_c-0.0.14.dist-info/top_level.txt
bencode_c-0.0.14.dist-info/RECORD
